utils/__init__.py
utils/baiduocr.py
utils/chaojiying.py
utils/filesearch.py
utils/misc.py
utils/sfun.py
ebanktool-1.0.2.dist-info/METADATA
ebanktool-1.0.2.dist-info/WHEEL
ebanktool-1.0.2.dist-info/top_level.txt
ebanktool-1.0.2.dist-info/RECORD
